pretix_paybox
