Metadata-Version: 2.1
Name: pretix-paybox
Version: 0.9.9
Summary: Paybox payment plugin for Pretix 4
Author-email: Ronan Le Meillat <ronan@highcanfly.club>
Maintainer-email: Ronan Le Meillat <ronan@highcanfly.club>
License: AGPLv3
Project-URL: homepage, https://github.com/highcanfly-club/pretix-paybox
Project-URL: repository, https://github.com/highcanfly-club/pretix-paybox
Keywords: pretix
License-File: LICENSE
